LICENSE
README.md
setup.py
src/pySummarizedExperiment/__init__.py
src/pySummarizedExperiment/pySummarizedExperiment.py
src/pySummarizedExperiment.egg-info/PKG-INFO
src/pySummarizedExperiment.egg-info/SOURCES.txt
src/pySummarizedExperiment.egg-info/dependency_links.txt
src/pySummarizedExperiment.egg-info/requires.txt
src/pySummarizedExperiment.egg-info/top_level.txt