Metadata-Version: 2.1
Name: pySummarizedExperiment
Version: 0.1.1
Summary: A Python port of R's SummarizedExperiment package
Home-page: https://github.com/Pascallio/pySummarizedExperiment
Author: Pascal Maas
Author-email: p.maas92@gmail.com
License: Apache-2.0
Platform: UNKNOWN
Classifier: Development Status :: 1 - Planning
Classifier: Intended Audience :: Science/Research
Classifier: License :: OSI Approved :: BSD License
Classifier: Operating System :: POSIX :: Linux
Classifier: Programming Language :: Python :: 3.9
